snippyng/__init__.py
snippyng/eigen_sound.py
snippyng/features.py
snippyng/locating.py
snippyng/text_to_sound.py
snippyng/util.py
snippyng/dacc/__init__.py
snippyng/dacc/mg.py
snippyng/others/__init__.py
snippyng/others/audio_tools.py
snippyng-0.0.3.dist-info/LICENSE
snippyng-0.0.3.dist-info/METADATA
snippyng-0.0.3.dist-info/WHEEL
snippyng-0.0.3.dist-info/top_level.txt
snippyng-0.0.3.dist-info/RECORD
