Metadata-Version: 2.1
Name: snippyng
Version: 0.0.3
Summary: Audio processing toolset
Home-page: https://github.com/thorwhalen/newut/tree/master/snippyng
Author: Thor Whalen
License: mit
Platform: any
License-File: LICENSE
